no_headers_target_csv.py
no_headers_target_csv-1.0.4.dist-info/LICENSE
no_headers_target_csv-1.0.4.dist-info/METADATA
no_headers_target_csv-1.0.4.dist-info/WHEEL
no_headers_target_csv-1.0.4.dist-info/entry_points.txt
no_headers_target_csv-1.0.4.dist-info/top_level.txt
no_headers_target_csv-1.0.4.dist-info/RECORD
