Metadata-Version: 2.1
Name: no-headers-target-csv
Version: 1.0.4
Summary: Singer.io target for writing CSV files
Home-page: https://singer.io
Author: Stitch
Author-email: UNKNOWN
License: UNKNOWN
Platform: UNKNOWN
Classifier: Programming Language :: Python :: 3 :: Only
Requires-Dist: jsonschema (==2.6.0)
Requires-Dist: singer-python (==2.1.4)
